libinfilect/__init__.py
libinfilect/aws.py
libinfilect/image.py
libinfilect/interface.py
libinfilect/misc.py
libinfilect/mongo.py
libinfilect/tensorflow_utils.py
libinfilect-0.0.3.dist-info/METADATA
libinfilect-0.0.3.dist-info/WHEEL
libinfilect-0.0.3.dist-info/top_level.txt
libinfilect-0.0.3.dist-info/RECORD
