Metadata-Version: 2.1
Name: libinfilect
Version: 0.0.3
Summary: Collection of frequently used utility functions
Home-page: https://bitbucket.org/infilect-ml-dev/libinfilect/
Author: Tushar Pawar
Author-email: tushar@infilect.com
License: UNKNOWN
Platform: UNKNOWN
Classifier: Programming Language :: Python :: 3
Classifier: Operating System :: OS Independent
